{"stat.craftItem.sky_orchards.sapling_sand":1,"stat.pickup.minecraft.wooden_slab":664,"stat.craftItem.minecraft.diamond_hoe":1,"stat.leaveGame":14,"stat.useItem.tconstruct.wooden_hopper":65,"stat.pickup.sky_orchards.resin_quartz":9,"stat.pickup.tconstruct.edible":30,"stat.mineBlock.rustic.leaves":46,"stat.mineBlock.tconstruct.channel":17,"stat.entityKilledBy.Human":1,"stat.killEntity.PigZombie":22,"stat.pickup.rustic.crushing_tub":4,"stat.pickup.tconstruct.faucet":7,"stat.craftItem.minecraft.shield":1,"stat.useItem.sky_orchards.sapling_copper":1,"stat.mineBlock.sky_orchards.log_dirt":1071,"stat.pickup.sky_orchards.resin_cottonwood":295,"stat.pickup.minecraft.rotten_flesh":43,"stat.pickup.sky_orchards.acorn_diamond":7,"stat.craftItem.sky_orchards.amber_clay":32,"stat.useItem.minecraft.diamond_hoe":82,"stat.craftItem.telepastries.nether_cake":1,"stat.craftItem.sky_orchards.sapling_gravel":1,"stat.pickup.sky_orchards.sapling_dirt":3045,"stat.craftItem.minecraft.stone_axe":105,"stat.pickup.sky_orchards.resin_emerald":17,"stat.pickup.minecraft.bucket":8,"stat.mineBlock.minecraft.wooden_slab":541,"stat.killEntity.Witch":2,"stat.mineBlock.rustic.log":9,"stat.pickup.sky_orchards.resin_petrified":1637,"stat.useItem.tconstruct.slime_sapling":2,"stat.mineBlock.ceramics.clay_barrel":16,"stat.pickup.xlfoodmod.lettuce":108,"stat.useItem.minecraft.iron_pickaxe":11,"stat.pickup.tconstruct.seared_glass":14,"stat.craftItem.minecraft.bed":1,"stat.pickup.cyclicmagic.item_pump":21,"stat.mineBlock.minecraft.hopper":12,"stat.pickup.thermalfoundation.material":6,"stat.craftItem.tp.iron_cobblegen_block":3,"stat.furnaceInteraction":628,"stat.useItem.minecraft.nether_wart":20,"stat.mineBlock.telepastries.overworld_cake":1,"stat.killEntity.ZombieVillager":4,"stat.useItem.sky_orchards.sapling_gold":1,"stat.mineBlock.sky_orchards.amber_iron":1,"stat.mineBlock.sky_orchards.leaves_quartz":53,"stat.entityKilledBy.WitherSkeleton":1,"stat.craftItem.sky_orchards.acorn_dirt":378,"stat.pickup.sky_orchards.acorn_coal":25,"stat.pickup.minecraft.beef":8,"stat.pickup.morecauldrons.brick_cauldron":14,"stat.pickup.sky_orchards.acorn_dirt":1208,"stat.useItem.minecraft.trapdoor":1,"stat.pickup.inspirations.potato_seeds":32,"stat.pickup.sky_orchards.sapling_coal":25,"stat.useItem.minecraft.fence":566,"stat.useItem.xlfoodmod.lettuce_seeds":68,"stat.mineBlock.sky_orchards.log_quartz":5,"stat.mineBlock.minecraft.fence":110,"stat.pickup.tconstruct.smeltery_io":11,"stat.pickup.tp.iron_cobblegen_block":1,"stat.useItem.minecraft.wheat_seeds":166,"stat.mineBlock.sky_orchards.log_tin":12,"stat.craftItem.minecraft.dropper":64,"stat.pickup.sky_orchards.leaves_coal":9,"stat.useItem.minecraft.dye":1135,"stat.pickup.sky_orchards.sapling_copper":8,"stat.craftItem.conarm.travel_belt_base":1,"stat.pickup.minecraft.lever":2,"stat.deaths":7,"stat.useItem.tconstruct.smeltery_io":15,"stat.pickup.minecraft.egg":38,"stat.pickup.sky_orchards.leaves_dirt":2,"stat.craftItem.minecraft.iron_pickaxe":1,"stat.pickup.sky_orchards.sapling_lapis":11,"stat.craftItem.conarm.armorstation":1,"stat.mineBlock.minecraft.tallgrass":224,"stat.useItem.sky_orchards.sapling_sand":46,"stat.pickup.tconstruct.seared":867,"stat.chestOpened":3144,"stat.pickup.sky_orchards.acorn_quartz":8,"stat.pickup.inspirations.stone_crook":4,"stat.pickup.minecraft.arrow":21,"stat.pickup.sky_orchards.resin_redstone":9,"stat.pickup.sky_orchards.acorn_bacon":8,"stat.mineBlock.rustic.deathstalk_mushroom":4,"stat.useItem.tp.cobblegen_block":2,"stat.mineBlock.sky_orchards.leaves_iron":570,"stat.craftItem.minecraft.quartz_block":4,"stat.craftItem.minecraft.coal":2781,"stat.useItem.sky_orchards.sapling_silver":1,"stat.pickup.tconstruct.cast_custom":2,"stat.useItem.sky_orchards.sapling_gravel":113,"stat.craftItem.sky_orchards.sapling_redstone":1,"stat.pickup.minecraft.carrot":548,"stat.crouchOneCm":584536,"stat.mineBlock.minecraft.chest":73,"stat.craftItem.minecraft.diamond":34,"stat.craftItem.minecraft.iron_ingot":5819,"stat.pickup.bonsaitrees.bonsaipot":161,"stat.craftItem.minecraft.hopper":641,"stat.pickup.sky_orchards.resin_lapis":10,"stat.craftItem.xlfoodmod.cooked_dough":8,"stat.craftingTableInteraction":590,"stat.mineBlock.tconstruct.rack":8,"stat.craftItem.cyclicmagic.trash":1,"stat.pickup.sky_orchards.sapling_tin":14,"stat.craftItem.tconstruct.pattern":644,"stat.pickup.sky_orchards.acorn_redstone":4,"stat.useItem.minecraft.reeds":7,"stat.mineBlock.tconstruct.smeltery_io":11,"stat.craftItem.tconstruct.seared_glass":30,"stat.pickup.minecraft.dye":66,"stat.pickup.minecraft.planks":672,"stat.pickup.sky_orchards.resin_iron":94,"stat.craftItem.minecraft.diamond_shovel":1,"stat.pickup.minecraft.wheat_seeds":1233,"stat.craftItem.sky_orchards.acorn_iron":1,"stat.craftItem.tconstruct.slime_congealed":62,"stat.craftItem.tconstruct.seared_furnace_controller":1,"stat.pickup.darkutils.material":10,"stat.drop.sky_orchards.acorn_iron":3,"stat.mineBlock.minecraft.dirt":481,"stat.pickup.sky_orchards.acorn_iron":112,"stat.pickup.minecraft.poisonous_potato":30,"stat.mineBlock.sky_orchards.leaves_lapis":49,"stat.useItem.ceramics.clay_barrel":9,"stat.useItem.minecraft.bread":5,"stat.pickup.sky_orchards.sapling_iron":89,"stat.pickup.inspirations.carrot_seeds":34,"stat.craftItem.tp.toasted_bread":174,"stat.useItem.minecraft.cobblestone":76,"stat.mineBlock.minecraft.double_plant":5,"stat.mineBlock.sky_orchards.sapling_clay":1,"stat.pickup.sky_orchards.resin_gravel":1500,"stat.pickup.sky_orchards.resin_silver":8,"stat.craftItem.minecraft.gold_ingot":9,"stat.pickup.minecraft.hopper":6,"stat.pickup.minecraft.chicken":1,"stat.pickup.minecraft.apple":1,"stat.pickup.telepastries.nether_cake":1,"stat.pickup.slabmachines.workbench_slab":3,"stat.pickup.integrateddynamics.squeezer":5,"stat.mineBlock.sky_orchards.sapling_gravel":14,"stat.craftItem.minecraft.bucket":5,"stat.craftItem.minecraft.planks":16700,"stat.useItem.minecraft.iron_sword":58,"stat.itemEnchanted":1,"stat.craftItem.minecraft.dirt":1052,"stat.pickup.morecauldrons.oak_cauldron":2,"stat.pickup.sky_orchards.leaves_petrified":7,"stat.mineBlock.minecraft.log":27,"stat.craftItem.minecraft.wooden_door":6,"stat.useItem.rustic.sapling":1,"stat.useItem.minecraft.wooden_door":4,"stat.pickup.rustic.sapling_apple":11,"stat.craftItem.sky_orchards.sapling_donut":1,"stat.craftItem.storagenetwork.master":1,"stat.craftItem.minecraft.paper":441,"stat.useItem.sky_orchards.acorn_sand":1,"stat.pickup.minecraft.red_flower":9,"stat.mineBlock.sky_orchards.log_cottonwood":144,"stat.useItem.minecraft.wooden_axe":254,"stat.useItem.sky_orchards.sapling_netherrack":1,"stat.craftItem.minecraft.cobblestone":260,"stat.craftItem.morecauldrons.brick_cauldron":3,"stat.useItem.thermalfoundation.tool.bow_diamond":159,"stat.useItem.minecraft.iron_axe":234,"stat.mineBlock.minecraft.cobblestone":380,"stat.craftItem.tconstruct.edible":48,"stat.pickup.minecraft.flint":306,"stat.mineBlock.minecraft.yellow_flower":16,"stat.killEntity.Human":61,"stat.craftItem.sky_orchards.sapling_emerald":1,"stat.craftItem.minecraft.wool":15,"stat.pickup.pickletweaks.coal_piece":17,"stat.mineBlock.morecauldrons.oak_cauldron":2,"stat.mineBlock.sky_orchards.leaves_redstone":54,"stat.useItem.minecraft.stone_slab2":856,"stat.drop.tconstruct.wooden_hopper":3,"stat.craftItem.minecraft.furnace":11,"stat.craftItem.minecraft.lapis_block":21,"stat.useItem.minecraft.egg":4,"stat.pickup.tp.cobblegen_block":2,"stat.mineBlock.cyclicmagic.trash":7,"stat.craftItem.minecraft.iron_boots":1,"stat.mineBlock.sky_orchards.leaves_emerald":106,"stat.mineBlock.minecraft.obsidian":12,"stat.mineBlock.sky_orchards.leaves_dirt":9941,"stat.craftItem.sky_orchards.amber_gold":266,"stat.craftItem.cyclicmagic.item_pump":28,"stat.flyOneCm":1492336,"stat.mineBlock.sky_orchards.log_copper":5,"stat.timeSinceDeath":64961,"stat.useItem.minecraft.wooden_slab":8394,"stat.craftItem.minecraft.iron_block":262,"stat.killEntity.Bat":1,"stat.useItem.minecraft.potato":74,"stat.craftItem.tconstruct.seared":1174,"stat.pickup.minecraft.nether_wart":26,"stat.craftItem.telepastries.overworld_cake":3,"stat.useItem.tconstruct.rack":9,"stat.killEntity.Creeper":72,"stat.mineBlock.sky_orchards.leaves_diamond":53,"stat.useItem.tp.toasted_bread":140,"stat.pickup.minecraft.string":74,"stat.pickup.sky_orchards.amber_iron":3,"stat.mineBlock.minecraft.ladder":1,"stat.pickup.sky_orchards.resin_netherrack":15,"stat.craftItem.tconstruct.stone_stick":32,"stat.pickup.ceramics.clay_barrel":16,"stat.useItem.sky_orchards.sapling_petrified":223,"stat.craftItem.tconstruct.tooltables":4,"stat.pickup.sky_orchards.sapling_bacon":9,"stat.sprintOneCm":3532140,"stat.craftItem.minecraft.wooden_axe":13,"stat.useItem.carryon.tile_item":81,"stat.useItem.tconstruct.seared_stairs_brick":50,"stat.mineBlock.sky_orchards.leaves_petrified":10241,"stat.pickup.sky_orchards.sapling_emerald":10,"stat.craftItem.mysticalagriculture.tier1_inferium_seeds":1,"stat.pickup.sky_orchards.leaves_gravel":6,"stat.pickup.inspirations.wooden_crook":3,"stat.mineBlock.sky_orchards.log_donut":6,"stat.pickup.tconstruct.nuggets":13,"stat.craftItem.minecraft.wooden_pressure_plate":32,"stat.mineBlock.sky_orchards.log_lead":4,"stat.useItem.tconstruct.seared_tank":16,"stat.pickup.minecraft.vine":1,"stat.pickup.sky_orchards.resin_diamond":10,"stat.useItem.minecraft.ladder":8,"stat.mineBlock.bonsaitrees.bonsaipot":180,"stat.pickup.minecraft.iron_block":7,"stat.killEntity.Zombie":71,"stat.craftItem.minecraft.dye":1116,"stat.craftItem.minecraft.diamond_axe":2,"stat.drop.sky_orchards.leaves_iron":4,"stat.diveOneCm":30747,"stat.craftItem.minecraft.slime_ball":252,"stat.pickup.minecraft.wheat":1149,"stat.pickup.tconstruct.tooltables":4,"stat.mineBlock.tp.iron_cobblegen_block":1,"stat.craftItem.minecraft.ladder":6,"stat.mineBlock.sky_orchards.leaves_donut":55,"stat.mineBlock.tconstruct.seared_furnace_controller":27,"stat.craftItem.minecraft.cooked_porkchop":3,"stat.pickup.minecraft.stone_axe":3,"stat.mineBlock.tconstruct.slime_leaves":255,"stat.useItem.bonsaitrees.bonsaipot":273,"stat.pickup.minecraft.obsidian":12,"stat.pickup.storagenetwork.kabel":8,"stat.craftItem.sky_orchards.sapling_coal":2,"stat.pickup.sky_orchards.resin_clay":1368,"stat.craftItem.minecraft.diamond_sword":2,"stat.jump":11347,"stat.useItem.minecraft.sand":10,"stat.mineBlock.sky_orchards.leaves_nickel":55,"stat.pickup.minecraft.coal":927,"stat.pickup.minecraft.iron_ingot":72,"stat.pickup.tconstruct.seared_tank":30,"stat.mineBlock.sky_orchards.leaves_copper":53,"stat.craftItem.minecraft.lever":11,"stat.pickup.minecraft.gunpowder":14,"stat.craftItem.minecraft.torch":1004,"stat.mineBlock.sky_orchards.log_sand":239,"stat.pickup.minecraft.dirt":631,"stat.craftItem.sky_orchards.sapling_lapis":1,"stat.pickup.rustic.log":9,"stat.pickup.sky_orchards.resin_bone":214,"stat.useItem.minecraft.sapling":4,"stat.craftItem.tcomplement.melter":1,"stat.mineBlock.sky_orchards.log_emerald":10,"stat.damageTaken":9790,"stat.pickup.cyclicmagic.trash":7,"stat.mineBlock.minecraft.torch":231,"stat.mineBlock.minecraft.red_flower":9,"stat.pickup.minecraft.magma_cream":4,"stat.craftItem.sky_orchards.amber_lead":1,"stat.useItem.sky_orchards.amber_iron":1,"stat.pickup.minecraft.potato":1527,"stat.mineBlock.minecraft.fence_gate":1,"stat.useItem.cyclicmagic.tool_push":2,"stat.pickup.sky_orchards.sapling_clay":815,"stat.killEntity.bouncy_creepers.bouncy_creeper":5,"stat.craftItem.minecraft.stone_slab":384,"stat.craftItem.sky_orchards.amber_petrified":12,"stat.animalsBred":34,"stat.useItem.minecraft.chest":614,"stat.craftItem.tconstruct.smeltery_io":22,"stat.pickup.tcomplement.melter":16,"stat.pickup.sky_orchards.acorn_nickel":9,"stat.pickup.sky_orchards.sapling_bone":154,"stat.pickup.sky_orchards.leaves_sand":33,"stat.useItem.minecraft.lava_bucket":15,"stat.craftItem.morecauldrons.oak_cauldron":2,"stat.craftItem.sky_orchards.amber_silver":1,"stat.pickup.sky_orchards.sapling_donut":9,"stat.useItem.cyclicmagic.heart_food":1,"stat.useItem.tconstruct.faucet":12,"stat.useItem.sky_orchards.sapling_lead":1,"stat.drop.inspirations.wooden_crook":1,"stat.pickup.sky_orchards.acorn_netherrack":15,"stat.craftItem.rustic.crushing_tub":4,"stat.mineBlock.sky_orchards.leaves_lead":56,"stat.mineBlock.sky_orchards.log_diamond":5,"stat.mineBlock.advancementbook.advancement_bookstand":1,"stat.craftItem.minecraft.iron_chestplate":1,"stat.drop.minecraft.wooden_slab":8,"stat.pickup.minecraft.ladder":3,"stat.useItem.minecraft.netherrack":37,"stat.craftItem.minecraft.bookshelf":30,"stat.mobKills":598,"stat.mineBlock.sky_orchards.log_gold":4,"stat.useItem.minecraft.boat":1,"stat.mineBlock.tconstruct.wooden_hopper":47,"stat.pickup.minecraft.beetroot_seeds":502,"stat.mineBlock.rustic.crushing_tub":4,"stat.pickup.minecraft.torch":337,"stat.drop.minecraft.stone_axe":1,"stat.mineBlock.sky_orchards.log_nickel":6,"stat.mineBlock.tp.cobblegen_block":4,"stat.useItem.inspirations.sugar_cane_seeds":44,"stat.pickup.rustic.ironberries":2,"stat.mineBlock.sky_orchards.log_petrified":1044,"stat.pickup.tconstruct.book":1,"stat.craftItem.sky_orchards.sapling_cottonwood":1,"stat.mineBlock.tconstruct.seared_tank":30,"stat.useItem.sky_orchards.sapling_cottonwood":28,"stat.useItem.inspirations.potato_seeds":22,"stat.pickup.tconstruct.wooden_hopper":33,"stat.useItem.minecraft.bookshelf":27,"stat.pickup.xlfoodmod.coffee":1,"stat.craftItem.minecraft.iron_axe":4,"stat.killEntity.Blaze":69,"stat.craftItem.storagenetwork.request":1,"stat.pickup.sky_orchards.resin_lead":6,"stat.useItem.minecraft.planks":2460,"stat.mineBlock.sky_orchards.leaves_tin":109,"stat.craftItem.sky_orchards.sapling_petrified":1,"stat.pickup.matteroverdrive.phaser_rifle":1,"stat.pickup.minecraft.porkchop":1,"stat.craftItem.xlfoodmod.donut":4,"stat.craftItem.horsepower.hand_grindstone":1,"stat.mineBlock.sky_orchards.log_bacon":4,"stat.useItem.sky_orchards.sapling_iron":13,"stat.useItem.minecraft.water_bucket":62,"stat.drop.sky_orchards.sapling_petrified":12,"stat.pickup.minecraft.sand":2,"stat.useItem.inspirations.carrot_seeds":25,"stat.craftItem.tconstruct.casting":13,"stat.pickup.sky_orchards.resin_bacon":7,"stat.craftItem.minecraft.stone_sword":5,"stat.mineBlock.minecraft.sand":2,"stat.pickup.storagenetwork.request":1,"stat.pickup.inspirations.mulch":9,"stat.mineBlock.sky_orchards.leaves_netherrack":108,"stat.craftItem.minecraft.blaze_powder":46,"stat.hopperInspected":117,"stat.useItem.minecraft.fence_gate":9,"stat.pickup.tconstruct.slime_sapling":36,"stat.pickup.sky_orchards.sapling_nickel":12,"stat.useItem.tconstruct.channel":16,"stat.useItem.minecraft.oak_stairs":138,"stat.pickup.xlfoodmod.lettuce_seeds":90,"stat.craftItem.thermalfoundation.material":16,"stat.mineBlock.sky_orchards.leaves_gold":54,"stat.pickup.minecraft.fence_gate":1,"stat.craftItem.xlfoodmod.dough":8,"stat.useItem.morecauldrons.brick_cauldron":5,"stat.pickup.minecraft.furnace":8,"stat.mineBlock.tconstruct.seared_stairs_brick":16,"stat.useItem.minecraft.redstone":1,"stat.mineBlock.tcomplement.melter":16,"stat.pickup.sky_orchards.acorn_copper":9,"stat.pickup.minecraft.skull":4,"stat.mineBlock.tconstruct.seared_glass":14,"stat.useItem.tconstruct.seared_glass":38,"stat.drop.sky_orchards.resin_lead":8,"stat.mineBlock.storagenetwork.kabel":8,"stat.craftItem.minecraft.sand":772,"stat.craftItem.minecraft.fence_gate":16,"stat.pickup.minecraft.pumpkin_seeds":12,"stat.pickup.tconstruct.slime_dirt":3,"stat.useItem.minecraft.hopper":464,"stat.craftItem.ceramics.clay_barrel_unfired":4,"stat.useItem.storagenetwork.kabel":8,"stat.craftItem.minecraft.heavy_weighted_pressure_plate":35,"stat.mineBlock.minecraft.oak_stairs":16,"stat.playOneMinute":2161324,"stat.pickup.tconstruct.rack":8,"stat.pickup.minecraft.blaze_rod":23,"stat.useItem.sky_orchards.acorn_dirt":383,"stat.pickup.mekanism.otherdust":33,"stat.mineBlock.storagenetwork.request":1,"stat.useItem.tp.iron_cobblegen_block":1,"stat.drop.xlfoodmod.flesh":1,"stat.pickup.minecraft.netherrack":118,"stat.mineBlock.sky_orchards.sapling_cottonwood":1,"stat.pickup.advancementbook.advancement_bookstand":1,"stat.pickup.tp.toasted_bread":1,"stat.pickup.tconstruct.casting":15,"stat.craftItem.tp.cobblegen_block":3,"stat.mineBlock.minecraft.netherrack":119,"stat.craftItem.storagenetwork.kabel":184,"stat.pickup.sky_orchards.acorn_petrified":1117,"stat.craftItem.sky_orchards.sapling_diamond":1,"stat.useItem.inspirations.wooden_crook":2241,"stat.pickup.sky_orchards.resin_sand":613,"stat.mineBlock.tconstruct.faucet":7,"stat.pickup.tconstruct.seared_furnace_controller":27,"stat.craftItem.minecraft.iron_hoe":4,"stat.craftItem.minecraft.iron_nugget":126,"stat.pickup.sky_orchards.resin_gold":6,"stat.fallOneCm":654909,"stat.craftItem.inspirations.mulch":648,"stat.pickup.sky_orchards.leaves_bone":34,"stat.craftItem.tconstruct.wooden_hopper":30,"stat.pickup.minecraft.melon_seeds":17,"stat.pickup.sky_orchards.sapling_netherrack":9,"stat.craftItem.minecraft.chest":1279,"stat.useItem.inspirations.mulch":3,"stat.mineBlock.minecraft.lever":3,"stat.useItem.minecraft.iron_hoe":494,"stat.pickup.resourcehogs.bacon":2,"stat.useItem.cyclicmagic.inventory_food":2,"stat.mineBlock.sky_orchards.leaves_sand":2443,"stat.pickup.sky_orchards.sapling_sand":652,"stat.pickup.sky_orchards.resin_tin":20,"stat.drop.minecraft.bone":3,"stat.useItem.minecraft.furnace":5,"stat.craftItem.tconstruct.materials":1760,"stat.pickup.tconstruct.channel":17,"stat.pickup.storagenetwork.master":1,"stat.pickup.tconstruct.seared_stairs_brick":16,"stat.pickup.sky_orchards.sapling_gold":7,"stat.pickup.matteroverdrive.weapon_module_barrel":1,"stat.mineBlock.sky_orchards.sapling_petrified":17,"stat.useItem.minecraft.stone_pickaxe":1018,"stat.craftItem.tconstruct.seared_tank":13,"stat.drop.tconstruct.seared":1,"stat.useItem.minecraft.stone_sword":291,"stat.craftItem.minecraft.iron_leggings":1,"stat.mineBlock.sky_orchards.log_bone":142,"stat.useItem.pickletweaks.diamond_paxel":188,"stat.craftItem.minecraft.oak_stairs":128,"stat.craftItem.sky_orchards.amber_tin":1,"stat.craftItem.minecraft.leather":2,"stat.craftItem.integrateddynamics.squeezer":1,"stat.drop.sky_orchards.acorn_sand":1,"stat.useItem.minecraft.torch":1216,"stat.craftItem.tconstruct.channel":9,"stat.mineBlock.sky_orchards.sapling_dirt":6,"stat.pickup.sky_orchards.leaves_clay":39,"stat.craftItem.minecraft.redstone_block":64,"stat.pickup.advancementbook.advancement_book":3,"stat.pickup.minecraft.crafting_table":16,"stat.useItem.minecraft.log":60,"stat.pickup.sky_orchards.acorn_gold":4,"stat.craftItem.minecraft.crafting_table":20,"stat.mineBlock.storagenetwork.master":1,"stat.craftItem.ceramics.clay_bucket":7,"stat.mineBlock.morecauldrons.brick_cauldron":14,"stat.craftItem.minecraft.boat":1,"stat.pickup.minecraft.iron_hoe":1,"stat.killEntity.LavaSlime":40,"stat.pickup.minecraft.log":7232,"stat.pickup.matteroverdrive.rogue_android_part":1,"stat.pickup.sky_orchards.acorn_sand":833,"stat.drop.minecraft.planks":5,"stat.craftItem.bibliocraft.table":1,"stat.craftItem.sky_orchards.acorn_sand":1,"stat.pickup.minecraft.sapling":28,"stat.mineBlock.minecraft.iron_block":2,"stat.useItem.xlfoodmod.donut":1,"stat.craftItem.tconstruct.smeltery_controller":1,"stat.pickup.minecraft.beetroot":471,"stat.killEntity.rogue_android":64,"stat.killEntity.WitherSkeleton":28,"stat.mineBlock.sky_orchards.log_clay":477,"stat.pickup.sky_orchards.acorn_lapis":6,"stat.craftItem.minecraft.sugar":58,"stat.mineBlock.sky_orchards.leaves_bacon":54,"stat.useItem.sky_orchards.sapling_nickel":1,"stat.useItem.minecraft.beetroot_seeds":97,"stat.sneakTime":146117,"stat.pickup.sky_orchards.sapling_diamond":11,"stat.drop.minecraft.bucket":2,"stat.pickup.rustic.deathstalk_mushroom":11,"stat.pickup.minecraft.yellow_flower":15,"stat.craftItem.slabmachines.workbench_slab":2,"stat.useItem.sky_orchards.sapling_dirt":216,"stat.mineBlock.sky_orchards.log_netherrack":9,"stat.pickup.minecraft.chest":74,"stat.craftItem.minecraft.enchanting_table":1,"stat.pickup.minecraft.bone":55,"stat.craftItem.ceramics.unfired_clay":7,"stat.mineBlock.sky_orchards.leaves_gravel":4371,"stat.craftItem.sky_orchards.sapling_quartz":1,"stat.craftItem.tconstruct.faucet":20,"stat.mineBlock.sky_orchards.leaves_silver":55,"stat.pickup.sky_orchards.resin_dirt":2799,"stat.useItem.minecraft.diamond_sword":898,"stat.craftItem.sky_orchards.amber_iron":1890,"stat.swimOneCm":45243,"stat.climbOneCm":36439,"stat.useItem.rustic.crushing_tub":6,"stat.pickup.tconstruct.slime_leaves":41,"stat.craftItem.inspirations.stone_crook":144,"stat.useItem.sky_orchards.sapling_bone":26,"stat.useItem.minecraft.dirt":1373,"stat.entityKilledBy.ranged_rogue_android":1,"stat.craftItem.sky_orchards.sapling_bone":1,"stat.craftItem.extendedcrafting.handheld_table":1,"stat.craftItem.minecraft.trapdoor":1,"stat.craftItem.minecraft.stone_pickaxe":24,"stat.pickup.minecraft.cobblestone":513,"stat.craftItem.pickletweaks.coal_piece":12,"stat.craftItem.advancementbook.advancement_bookstand":1,"stat.craftItem.minecraft.glass_bottle":3,"stat.useItem.cyclicmagic.item_pump":21,"stat.pickup.sky_orchards.sapling_lead":6,"stat.pickup.sky_orchards.resin_coal":16,"stat.craftItem.minecraft.wooden_slab":9582,"stat.useItem.minecraft.cooked_beef":2,"stat.pickup.minecraft.cactus":112,"stat.pickup.sky_orchards.sapling_petrified":1791,"stat.pickup.minecraft.redstone":2,"stat.craftItem.minecraft.book":94,"stat.mineBlock.sky_orchards.leaves_cottonwood":1487,"stat.pickup.sky_orchards.resin_nickel":11,"stat.killEntity.ranged_rogue_android":63,"stat.mineBlock.sky_orchards.sapling_sand":1,"stat.craftItem.minecraft.cake":4,"stat.useItem.slabmachines.workbench_slab":3,"stat.pickup.minecraft.wooden_axe":1,"stat.pickup.rustic.sapling":11,"stat.useItem.sky_orchards.sapling_clay":90,"stat.pickup.minecraft.trapdoor":1,"stat.drop.minecraft.beetroot_seeds":1,"stat.craftItem.tconstruct.soil":1762,"stat.pickup.tconstruct.smeltery_controller":16,"stat.craftItem.sky_orchards.sapling_netherrack":1,"stat.useItem.tconstruct.edible":1,"stat.mineBlock.sky_orchards.leaves_clay":4336,"stat.craftItem.minecraft.stone_slab2":0,"stat.pickup.sky_orchards.sapling_cottonwood":250,"stat.pickup.conarm.travel_belt":2,"stat.craftItem.minecraft.stick":404,"stat.craftItem.ceramics.clay_barrel":4,"stat.useItem.cyclicmagic.crafting_food":1,"stat.craftItem.tconstruct.seared_stairs_brick":40,"stat.craftItem.minecraft.stone":1056,"stat.useItem.sky_orchards.sapling_emerald":1,"stat.craftItem.conarm.travel_belt":1,"stat.useItem.tconstruct.casting":8,"stat.mineBlock.minecraft.crafting_table":16,"stat.useItem.minecraft.diamond_pickaxe":673,"stat.useItem.minecraft.carrot":74,"stat.craftItem.animalcrops.seeds":6,"stat.craftItem.minecraft.clay_ball":1608,"stat.pickup.sky_orchards.resin_copper":7,"stat.mineBlock.minecraft.planks":538,"stat.craftItem.minecraft.soul_sand":5,"stat.drop":68,"stat.craftItem.sky_orchards.sapling_clay":1,"stat.mineBlock.rustic.leaves_apple":55,"stat.useItem.tconstruct.seared":1199,"stat.craftItem.minecraft.diamond_pickaxe":3,"stat.useItem.minecraft.melon_seeds":1,"stat.craftItem.pickletweaks.diamond_paxel":1,"stat.craftItem.minecraft.clay":544,"stat.useItem.inspirations.stone_crook":32759,"stat.pickup.sky_orchards.acorn_cottonwood":193,"stat.mineBlock.sky_orchards.leaves_bone":1387,"stat.pickup.minecraft.gravel":38,"stat.useItem.minecraft.glass_bottle":3,"stat.mineBlock.tconstruct.smeltery_controller":16,"stat.useItem.minecraft.diamond_axe":420,"stat.mineBlock.minecraft.deadbush":1,"stat.mineBlock.rustic.sapling":1,"stat.mineBlock.tconstruct.slime_dirt":2,"stat.pickup.minecraft.brick":33,"stat.pickup.sky_orchards.acorn_tin":8,"stat.craftItem.tconstruct.rack":4,"stat.pickup.minecraft.fence":106,"stat.pickup.sky_orchards.sapling_redstone":7,"stat.craftItem.bonsaitrees.bonsaipot":320,"stat.pickup.sky_orchards.acorn_donut":7,"stat.useItem.minecraft.stone_axe":4298,"stat.craftItem.minecraft.bread":243,"stat.pickup.minecraft.spider_eye":3,"stat.craftItem.minecraft.iron_helmet":1,"stat.useItem.sky_orchards.sapling_tin":1,"stat.craftItem.tconstruct.book":1,"stat.pickup.tconstruct.slime_congealed":20,"stat.mineBlock.cyclicmagic.item_pump":21,"stat.boatOneCm":3651,"stat.pickup.sky_orchards.leaves_cottonwood":2,"stat.drop.inspirations.stone_crook":1,"stat.pickup.inspirations.sugar_cane_seeds":67,"stat.mineBlock.tconstruct.tooltables":4,"stat.mineBlock.sky_orchards.log_lapis":5,"stat.drop.minecraft.iron_hoe":1,"stat.pickup.minecraft.leather":3,"stat.mineBlock.minecraft.furnace":8,"stat.pickup.mysticalagriculture.crafting":23,"stat.pickup.minecraft.reeds":1200,"stat.craftItem.sky_orchards.amber_copper":1,"stat.mineBlock.sky_orchards.log_redstone":5,"stat.pickup.tconstruct.materials":5,"stat.pickup.minecraft.oak_stairs":15,"stat.pickup.sky_orchards.sapling_quartz":10,"stat.damageDealt":48344,"stat.craftItem.minecraft.glass":258,"stat.craftItem.resourcehogs.mud_bucket":1,"stat.sleepInBed":17,"stat.mineBlock.sky_orchards.log_iron":65,"stat.killEntity.Cow":4,"stat.useItem.minecraft.crafting_table":7,"stat.craftItem.minecraft.gravel":449,"stat.craftItem.minecraft.iron_sword":1,"stat.pickup.sky_orchards.acorn_bone":974,"stat.mineBlock.integrateddynamics.squeezer":5,"stat.walkOneCm":7177704,"stat.pickup.ceramics.clay_bucket":1,"stat.pickup.sky_orchards.resin_donut":10,"stat.useItem.morecauldrons.oak_cauldron":1,"stat.pickup.minecraft.stick":243,"stat.craftItem.sky_orchards.sapling_bacon":1,"stat.craftItem.inspirations.wooden_crook":46,"stat.pickup.sky_orchards.acorn_clay":589,"stat.pickup.rustic.apple_seeds":1,"stat.mineBlock.sky_orchards.log_silver":6,"stat.pickup.sky_orchards.acorn_emerald":13,"stat.craftItem.thermalfoundation.tool.bow_diamond":1,"stat.mineBlock.sky_orchards.log_gravel":480,"stat.mineBlock.slabmachines.workbench_slab":2,"stat.pickup.sky_orchards.acorn_gravel":1191,"stat.craftItem.sky_orchards.amber_redstone":64,"stat.pickup.sky_orchards.acorn_silver":8,"stat.craftItem.minecraft.redstone":126,"stat.pickup.sky_orchards.sapling_gravel":1708,"stat.useItem.minecraft.cactus":10,"stat.pickup.sky_orchards.sapling_silver":7,"stat.killEntity.Skeleton":70,"stat.drop.sky_orchards.sapling_dirt":11,"stat.mineBlock.minecraft.cactus":31,"stat.killEntity.Chicken":1,"stat.useItem.minecraft.iron_block":2,"stat.killEntity.Spider":11,"stat.mineBlock.inspirations.mulch":3,"stat.pickup.minecraft.quartz":9,"stat.craftItem.minecraft.fence":495,"stat.craftItem.farmingforblockheads.market":1,"stat.pickup.minecraft.water_bucket":5,"stat.mineBlock.minecraft.leaves":162,"stat.mineBlock.tconstruct.seared":870,"stat.craftItem.sky_orchards.amber_nickel":16,"stat.mineBlock.tconstruct.casting":15,"stat.craftItem.minecraft.brick":802,"stat.pickup.xlfoodmod.donut":16,"stat.drop.tconstruct.book":1}